data/__init__.py
data/apify_tap/__init__.py
data/apify_tap/data_validator_prompt.txt
data/apify_tap/output_response_schema.json
data/apify_tap/prompt.txt
data/tap_manager/__init__.py
data/tap_manager/taps_index.json
data/taps/__init__.py
data/taps/atg_alexey_bestbuy_products_actor/__init__.py
data/taps/atg_alexey_bestbuy_products_actor/_actor-description-from-store-listing.json
data/taps/atg_alexey_bestbuy_products_actor/_actor-input-schema_original.json
data/taps/atg_alexey_bestbuy_products_actor/_actor_example_run_output.json
data/taps/atg_alexey_bestbuy_products_actor/_test-cases.json
data/taps/atg_alexey_bestbuy_products_actor/actor-description.json
data/taps/atg_alexey_bestbuy_products_actor/actor-input-example.json
data/taps/atg_alexey_bestbuy_products_actor/actor-input-json-schema.json
data/taps/atg_alexey_bestbuy_products_actor/actor-input-summary.json
data/taps/atg_alexey_bestbuy_products_actor/actor-output-fields.json
data/taps/atg_alexey_bestbuy_products_actor/tap-description.json
data/taps/atg_alexey_bestbuy_products_actor/tap-examples.json
data/taps/atg_alexey_bestbuy_products_actor/test-cases.json
data/taps/atg_alexey_pinterest_crawler/__init__.py
data/taps/atg_alexey_pinterest_crawler/_actor-description-from-store-listing.json
data/taps/atg_alexey_pinterest_crawler/_actor-input-schema_original.json
data/taps/atg_alexey_pinterest_crawler/_actor_example_run_output.json
data/taps/atg_alexey_pinterest_crawler/_test-cases.json
data/taps/atg_alexey_pinterest_crawler/actor-description.json
data/taps/atg_alexey_pinterest_crawler/actor-input-example.json
data/taps/atg_alexey_pinterest_crawler/actor-input-json-schema.json
data/taps/atg_alexey_pinterest_crawler/actor-input-summary.json
data/taps/atg_alexey_pinterest_crawler/actor-output-fields.json
data/taps/atg_alexey_pinterest_crawler/tap-description.json
data/taps/atg_alexey_pinterest_crawler/tap-examples.json
data/taps/atg_alexey_pinterest_crawler/test-cases.json
webtap-0.4.5.dist-info/LICENSE
webtap-0.4.5.dist-info/METADATA
webtap-0.4.5.dist-info/WHEEL
webtap-0.4.5.dist-info/top_level.txt
webtap-0.4.5.dist-info/RECORD
